pycachu/__init__.py
pycachu/cache.py
pycachu/errors.py
pycachu/validators.py
pycachuser-0.0.2.dist-info/LICENSE
pycachuser-0.0.2.dist-info/METADATA
pycachuser-0.0.2.dist-info/WHEEL
pycachuser-0.0.2.dist-info/top_level.txt
pycachuser-0.0.2.dist-info/RECORD
