Metadata-Version: 2.1
Name: pycachuser
Version: 0.0.2
Summary: Grabs and stores credentials in a human-readable yaml file, with passwords saved using the keyring module
Home-page: https://github.com/atommoran/pycachu
Author: Tom Moran
Author-email: tommorancodes@gmail.com
License: UNKNOWN
Project-URL: Bug Tracker, https://github.com/atommoran/pycachu/issues
Platform: UNKNOWN
Classifier: Programming Language :: Python :: 3
Classifier: License :: OSI Approved :: MIT License
Classifier: Operating System :: OS Independent
Requires-Python: >=3.6
License-File: LICENSE
